alibabacloud_config20200907/__init__.py
alibabacloud_config20200907/client.py
alibabacloud_config20200907/models/__init__.py
alibabacloud_config20200907/models/_active_aggregate_config_rules_request.py
alibabacloud_config20200907/models/_active_aggregate_config_rules_response.py
alibabacloud_config20200907/models/_active_aggregate_config_rules_response_body.py
alibabacloud_config20200907/models/_active_config_rules_request.py
alibabacloud_config20200907/models/_active_config_rules_response.py
alibabacloud_config20200907/models/_active_config_rules_response_body.py
alibabacloud_config20200907/models/_attach_aggregate_config_rule_to_compliance_pack_request.py
alibabacloud_config20200907/models/_attach_aggregate_config_rule_to_compliance_pack_response.py
alibabacloud_config20200907/models/_attach_aggregate_config_rule_to_compliance_pack_response_body.py
alibabacloud_config20200907/models/_attach_config_rule_to_compliance_pack_request.py
alibabacloud_config20200907/models/_attach_config_rule_to_compliance_pack_response.py
alibabacloud_config20200907/models/_attach_config_rule_to_compliance_pack_response_body.py
alibabacloud_config20200907/models/_copy_compliance_packs_request.py
alibabacloud_config20200907/models/_copy_compliance_packs_response.py
alibabacloud_config20200907/models/_copy_compliance_packs_response_body.py
alibabacloud_config20200907/models/_copy_config_rules_request.py
alibabacloud_config20200907/models/_copy_config_rules_response.py
alibabacloud_config20200907/models/_copy_config_rules_response_body.py
alibabacloud_config20200907/models/_create_advanced_search_file_request.py
alibabacloud_config20200907/models/_create_advanced_search_file_response.py
alibabacloud_config20200907/models/_create_advanced_search_file_response_body.py
alibabacloud_config20200907/models/_create_aggregate_advanced_search_file_request.py
alibabacloud_config20200907/models/_create_aggregate_advanced_search_file_response.py
alibabacloud_config20200907-4.1.0.dist-info/LICENSE
alibabacloud_config20200907-4.1.0.dist-info/METADATA
alibabacloud_config20200907-4.1.0.dist-info/WHEEL
alibabacloud_config20200907-4.1.0.dist-info/top_level.txt
alibabacloud_config20200907-4.1.0.dist-info/RECORD
